[
  {
    "ContainingType": "CollegeProject.Controllers.LoginController",
    "Method": "Login",
    "RelativePath": "api/Login/Login",
    "HttpMethod": "POST",
    "IsController": true,
    "Order": 0,
    "Parameters": [
      {
        "Name": "loginDetails",
        "Type": "CollegeProject.Models.LoginDetailsDto",
        "IsRequired": true
      }
    ],
    "ReturnTypes": []
  },
  {
    "ContainingType": "CollegeProject.Controllers.RegistrationController",
    "Method": "Registration",
    "RelativePath": "api/Registration/Registration",
    "HttpMethod": "POST",
    "IsController": true,
    "Order": 0,
    "Parameters": [
      {
        "Name": "registrationDTo",
        "Type": "CollegeProject.Models.RegistrationDTo",
        "IsRequired": true
      }
    ],
    "ReturnTypes": []
  },
  {
    "ContainingType": "CollegeProject.Controllers.RolesController",
    "Method": "CreateRole",
    "RelativePath": "api/Roles/CreateRole",
    "HttpMethod": "POST",
    "IsController": true,
    "Order": 0,
    "Parameters": [
      {
        "Name": "rolesDto",
        "Type": "CollegeProject.Models.Roles.RolesDto",
        "IsRequired": true
      }
    ],
    "ReturnTypes": []
  },
  {
    "ContainingType": "CollegeProject.Controllers.RolesController",
    "Method": "CreateRoleMapping",
    "RelativePath": "api/Roles/CreateRoleMapping",
    "HttpMethod": "POST",
    "IsController": true,
    "Order": 0,
    "Parameters": [
      {
        "Name": "controllerMappingDto",
        "Type": "CollegeProject.Models.Roles.RoleControllerMappingDto",
        "IsRequired": true
      }
    ],
    "ReturnTypes": []
  },
  {
    "ContainingType": "CollegeProject.Controllers.WeatherForecastController",
    "Method": "Get",
    "RelativePath": "WeatherForecast",
    "HttpMethod": "GET",
    "IsController": true,
    "Order": 0,
    "Parameters": [],
    "ReturnTypes": [
      {
        "Type": "System.Collections.Generic.IEnumerable\u00601[[CollegeProject.WeatherForecast, CollegeProject, Version=1.0.0.0, Culture=neutral, PublicKeyToken=null]]",
        "MediaTypes": [
          "text/plain",
          "application/json",
          "text/json"
        ],
        "StatusCode": 200
      }
    ],
    "EndpointName": "GetWeatherForecast"
  }
]